odoo10_addon_account_tax_analysis-10.0.1.0.0.99.dev9-py3.8-nspkg.pth
odoo/addons/account_tax_analysis/README.rst
odoo/addons/account_tax_analysis/__init__.py
odoo/addons/account_tax_analysis/__manifest__.py
odoo/addons/account_tax_analysis/i18n/account_tax_analysis.pot
odoo/addons/account_tax_analysis/i18n/ar.po
odoo/addons/account_tax_analysis/i18n/bg.po
odoo/addons/account_tax_analysis/i18n/bs.po
odoo/addons/account_tax_analysis/i18n/ca.po
odoo/addons/account_tax_analysis/i18n/ca_ES.po
odoo/addons/account_tax_analysis/i18n/cs.po
odoo/addons/account_tax_analysis/i18n/de.po
odoo/addons/account_tax_analysis/i18n/en_GB.po
odoo/addons/account_tax_analysis/i18n/es.po
odoo/addons/account_tax_analysis/i18n/es_CR.po
odoo/addons/account_tax_analysis/i18n/es_EC.po
odoo/addons/account_tax_analysis/i18n/es_ES.po
odoo/addons/account_tax_analysis/i18n/es_MX.po
odoo/addons/account_tax_analysis/i18n/es_VE.po
odoo/addons/account_tax_analysis/i18n/et.po
odoo/addons/account_tax_analysis/i18n/fr.po
odoo/addons/account_tax_analysis/i18n/gl.po
odoo/addons/account_tax_analysis/i18n/gl_ES.po
odoo/addons/account_tax_analysis/i18n/gu.po
odoo/addons/account_tax_analysis/i18n/hr.po
odoo/addons/account_tax_analysis/i18n/hu.po
odoo/addons/account_tax_analysis/i18n/id.po
odoo/addons/account_tax_analysis/i18n/it.po
odoo/addons/account_tax_analysis/i18n/ja.po
odoo/addons/account_tax_analysis/i18n/lt.po
odoo/addons/account_tax_analysis/i18n/mk.po
odoo/addons/account_tax_analysis/i18n/mn.po
odoo/addons/account_tax_analysis/i18n/nb.po
odoo/addons/account_tax_analysis/i18n/nl.po
odoo/addons/account_tax_analysis/i18n/nl_BE.po
odoo/addons/account_tax_analysis/i18n/pl.po
odoo/addons/account_tax_analysis/i18n/pt.po
odoo/addons/account_tax_analysis/i18n/pt_BR.po
odoo/addons/account_tax_analysis/i18n/ro.po
odoo/addons/account_tax_analysis/i18n/ru.po
odoo/addons/account_tax_analysis/i18n/sl.po
odoo/addons/account_tax_analysis/i18n/sr@latin.po
odoo/addons/account_tax_analysis/i18n/sv.po
odoo10_addon_account_tax_analysis-10.0.1.0.0.99.dev9.dist-info/METADATA
odoo10_addon_account_tax_analysis-10.0.1.0.0.99.dev9.dist-info/WHEEL
odoo10_addon_account_tax_analysis-10.0.1.0.0.99.dev9.dist-info/namespace_packages.txt
odoo10_addon_account_tax_analysis-10.0.1.0.0.99.dev9.dist-info/top_level.txt
odoo10_addon_account_tax_analysis-10.0.1.0.0.99.dev9.dist-info/RECORD
