Metadata-Version: 2.1
Name: odoo10-addon-account-tax-analysis
Version: 10.0.1.0.0.99.dev9
Summary: Tax analysis
Home-page: http://www.camptocamp.com
Author: Camptocamp SA, ACSONE SA/NV, Odoo Community Association (OCA)
Author-email: support@odoo-community.org
License: AGPL-3
Platform: UNKNOWN
Classifier: Programming Language :: Python
Classifier: Framework :: Odoo
Classifier: Framework :: Odoo :: 10.0
Classifier: License :: OSI Approved :: GNU Affero General Public License v3
Requires-Python: ~=2.7
Requires-Dist: odoo <10.1dev,>=10.0
